src/lobs/version.py
py_lobs-0.1.1.dist-info/METADATA
py_lobs-0.1.1.dist-info/WHEEL
py_lobs-0.1.1.dist-info/entry_points.txt
py_lobs-0.1.1.dist-info/licenses/LICENSE
py_lobs-0.1.1.dist-info/RECORD
