Metadata-Version: 2.4
Name: py-lobs
Version: 0.1.1
Project-URL: Documentation, https://github.com/rikardonm/lobs#readme
Project-URL: Issues, https://github.com/rikardonm/lobs/issues
Project-URL: Source, https://github.com/rikardonm/lobs
Author-email: Ricardo Marchesan <ricardo@azevem.com>
License-Expression: MIT
License-File: LICENSE
Classifier: Development Status :: 4 - Beta
Classifier: Programming Language :: Python
Classifier: Programming Language :: Python :: 3.12
Classifier: Programming Language :: Python :: Implementation :: CPython
Classifier: Programming Language :: Python :: Implementation :: PyPy
Requires-Python: >=3.12
Requires-Dist: click>=8.3.0
